{
	"system" : {
		"platform" : "windows64",
		"os_name" : "Windows 10",
		"os_version" : "10.0"
	},
	"error" : {
		"executable" : "quartus",
		"comment" : "not_applicable",
		"error_message" : "Access Violation at 0X00007FFE54377C80",
		"source_file" : "unknown",
		"line" : "0",
		"stack_trace" : "\t0x7ffe54377c7f: imetip + 0x77c7f (DllGetClassObject + 0x24c6f)\n\t0x7ffe5430bfb7: imetip + 0xbfb7\n\t0x7ffe54328c7a: imetip + 0x28c7a\n\t0x7ffe54328d33: imetip + 0x28d33\n\t0x7ffe54326ae7: imetip + 0x26ae7\n\t0x7ffe5433f932: imetip + 0x3f932\n\t0x7ffe5433bde1: imetip + 0x3bde1\n\t0x7ffe543893d5: imetip + 0x893d5 (DllGetClassObject + 0x363c5)\n\t0x7ffe5435381f: imetip + 0x5381f (DllGetClassObject + 0x80f)\n\t0x7ffe543ba2d8: imetip + 0xba2d8 (DllUnregisterServer + 0x1e6a8)\n\t0x7ffe543a0392: imetip + 0xa0392 (DllUnregisterServer + 0x4762)\n\t0x7ffe543889ad: imetip + 0x889ad (DllGetClassObject + 0x3599d)\n\t0x7ffe543a072b: imetip + 0xa072b (DllUnregisterServer + 0x4afb)\n\t0x7ffe5439d058: imetip + 0x9d058 (DllUnregisterServer + 0x1428)\n\t0x7ffe5439d6a5: imetip + 0x9d6a5 (DllUnregisterServer + 0x1a75)\n\t0x7ffe76540f75: MSCTF + 0x20f75 (CtfImeAssociateFocus + 0x90e5)\n\t0x7ffe76541aee: MSCTF + 0x21aee (CtfImeAssociateFocus + 0x9c5e)\n\t0x7ffe76543726: MSCTF + 0x23726 (CtfImeAssociateFocus + 0xb896)\n\t0x7ffe765607ce: MSCTF + 0x407ce (DllGetClassObject + 0x1b0e)\n\t0x7ffe76560831: MSCTF + 0x40831 (DllGetClassObject + 0x1b71)\n\t0x7ffe7654401f: MSCTF + 0x2401f (CtfImeAssociateFocus + 0xc18f)\n\t0x7ffe76537095: MSCTF + 0x17095 (TF_Notify + 0x1a5)\n\t0x7ffe766b3bef: USER32 + 0x23bef (FindWindowExA + 0x25f)\n\t0x7ffe766b02e8: USER32 + 0x202e8 (GetPropW + 0x298)\n\t0x7ffe766b01fd: USER32 + 0x201fd (GetPropW + 0x1ad)\n\t0x7ffe78f490b3: ntdll + 0xa90b3 (KiUserCallbackDispatcher + 0x23)\n\t0x7ffe761423c3: win32u + 0x23c3 (NtUserDestroyWindow + 0x13)\n\t 0x5db562b1: QtGui4 + 0x962b1 (?destroy@QWidget@@IEAAX_N0@Z + 0x1f1)\n\t 0x5db1c370: QtGui4 + 0x5c370 (??1QWidget@@UEAA@XZ + 0x7d0)\n\t0x7ffe5b855f74: SYS_QUI + 0x65f74 (??_EQLineEdit@@UEAAPEAXI@Z + 0x14)\n\t 0x5db32d7a: QtGui4 + 0x72d7a (??1QWidgetAction@@UEAA@XZ + 0x12a)\n\t 0x5db32e15: QtGui4 + 0x72e15 (??1QWidgetAction@@UEAA@XZ + 0x1c5)\n\t 0x5d8ee472: QtCore4 + 0x11e472 (?deleteChildren@QObjectPrivate@@QEAAXXZ + 0xa2)\n\t 0x5db1c347: QtGui4 + 0x5c347 (??1QWidget@@UEAA@XZ + 0x7a7)\n\t0x7ffe5b855fc7: SYS_QUI + 0x65fc7 (??_EQUI_SEARCH_TOOLBAR@@UEAAPEAXI@Z + 0x37)\n\t 0x5d8ee472: QtCore4 + 0x11e472 (?deleteChildren@QObjectPrivate@@QEAAXXZ + 0xa2)\n\t 0x5db1c347: QtGui4 + 0x5c347 (??1QWidget@@UEAA@XZ + 0x7a7)\n\t 0x5de7e9aa: QtGui4 + 0x3be9aa (??1QMenuBar@@UEAA@XZ + 0x18a)\n\t 0x5d8ee472: QtCore4 + 0x11e472 (?deleteChildren@QObjectPrivate@@QEAAXXZ + 0xa2)\n\t 0x5db1c347: QtGui4 + 0x5c347 (??1QWidget@@UEAA@XZ + 0x7a7)\n\t0x7ffe5ba65205: SYS_QGQ + 0x5205 (??_EQGQ_MAIN_WINDOW@@UEAAPEAXI@Z + 0x55)\n\t 0x5d8ef9b4: QtCore4 + 0x11f9b4 (?event@QObject@@UEAA_NPEAVQEvent@@@Z + 0xa4)\n\t 0x5db21402: QtGui4 + 0x61402 (?event@QWidget@@MEAA_NPEAVQEvent@@@Z + 0xd42)\n\t 0x5de59d30: QtGui4 + 0x399d30 (?event@QMainWindow@@MEAA_NPEAVQEvent@@@Z + 0x280)\n\t 0x5dae2e95: QtGui4 + 0x22e95 (?notify_helper@QApplicationPrivate@@QEAA_NPEAVQObject@@PEAVQEvent@@@Z + 0xf5)\n\t 0x5dae2b2f: QtGui4 + 0x22b2f (?notify@QApplication@@UEAA_NPEAVQObject@@PEAVQEvent@@@Z + 0x17bf)\n\t 0x5d8dd92b: QtCore4 + 0x10d92b (?notifyInternal@QCoreApplication@@AEAA_NPEAVQObject@@PEAVQEvent@@@Z + 0x7b)\n\t 0x5d8df502: QtCore4 + 0x10f502 (?sendPostedEvents@QCoreApplicationPrivate@@SAXPEAVQObject@@HPEAVQThreadData@@@Z + 0x2b2)\n\t 0x5d902fb8: QtCore4 + 0x132fb8 (?processEvents@QEventDispatcherWin32@@UEAA_NV?$QFlags@W4ProcessEventsFlag@QEventLoop@@@@@Z + 0xb98)\n\t0x7ffe7669bc4f: USER32 + 0xbc4f (CallWindowProcW + 0x4cf)\n\t0x7ffe7669b5ce: USER32 + 0xb5ce (DispatchMessageW + 0x1ae)\n\t 0x5d902802: QtCore4 + 0x132802 (?processEvents@QEventDispatcherWin32@@UEAA_NV?$QFlags@W4ProcessEventsFlag@QEventLoop@@@@@Z + 0x3e2)\n\t 0x5db40eb4: QtGui4 + 0x80eb4 (?openPopup@QApplicationPrivate@@QEAAXPEAVQWidget@@@Z + 0x204)\n\t 0x5d8da88b: QtCore4 + 0x10a88b (?exec@QEventLoop@@QEAAHV?$QFlags@W4ProcessEventsFlag@QEventLoop@@@@@Z + 0x22b)\n\t 0x5d8dce6f: QtCore4 + 0x10ce6f (?exec@QCoreApplication@@SAHXZ + 0xdf)\n\t0x7ff6125a197b: quartus + 0x197b (?qgq_main@@YAHHPEAPEBD@Z + 0x7b)\n\t0x7ffe667b3328: CCL_MSG + 0x13328 (?msg_main_thread@@YAPEAXPEAX@Z + 0x18)\n\t0x7ffe667b4b0e: CCL_MSG + 0x14b0e (?msg_thread_wrapper@@YAPEAXP6APEAXPEAX@Z0@Z + 0x6e)\n\t0x7ffe668c5b00: ccl_mem + 0x15b00 (?mem_thread_wrapper@@YAPEAXP6APEAXPEAX@Z0@Z + 0x70)\n\t0x7ffe667b2a11: CCL_MSG + 0x12a11 (?msg_exe_main@@YAHHPEAPEBDP6AHH0@Z@Z + 0xa1)\n\t0x7ff6125a24e7: quartus + 0x24e7 (WinMain + 0x127)\n\t0x7ff6125a1e58: quartus + 0x1e58 (__tmainCRTStartup + 0x148)\n\t0x7ffe78da2773: KERNEL32 + 0x12773 (BaseThreadInitThunk + 0x13)\n\t0x7ffe78f10d60: ntdll + 0x70d60 (RtlUserThreadStart + 0x20)\n",
		"subsystem" : "unknown"
	},
	"quartus" : {
		"quartus_bits" : "64",
		"version" : "16.1.0",
		"build" : "196",
		"edition" : "Lite Edition"
	}
}